pydis_core/__init__.py
pydis_core/_bot.py
pydis_core/async_stats.py
pydis_core/exts/__init__.py
pydis_core/py.typed
pydis_core/site_api.py
pydis_core/utils/__init__.py
pydis_core/utils/_extensions.py
pydis_core/utils/_monkey_patches.py
pydis_core/utils/caching.py
pydis_core/utils/channel.py
pydis_core/utils/checks.py
pydis_core/utils/commands.py
pydis_core/utils/cooldown.py
pydis_core/utils/error_handling/__init__.py
pydis_core/utils/error_handling/commands/__init__.py
pydis_core/utils/error_handling/commands/abc.py
pydis_core/utils/error_handling/commands/manager.py
pydis_core/utils/function.py
pydis_core/utils/interactions.py
pydis_core/utils/lock.py
pydis_core/utils/logging.py
pydis_core/utils/members.py
pydis_core/utils/messages.py
pydis_core/utils/pagination.py
pydis_core/utils/paste_service.py
pydis_core/utils/regex.py
pydis_core/utils/scheduling.py
pydis_core-11.8.0.dist-info/METADATA
pydis_core-11.8.0.dist-info/WHEEL
pydis_core-11.8.0.dist-info/licenses/LICENSE
pydis_core-11.8.0.dist-info/RECORD
